czapi/__init__.py
czapi/_nbdev.py
czapi/api.py
czapi/core/__init__.py
czapi/core/errors.py
czapi/core/testing.py
czapi/core/utils.py
czapi/core/scraping/__init__.py
czapi/core/scraping/base.py
czapi/core/scraping/constants.py
czapi/core/scraping/event.py
czapi/core/scraping/linescore.py
czapi-0.2.0.dist-info/LICENSE
czapi-0.2.0.dist-info/METADATA
czapi-0.2.0.dist-info/WHEEL
czapi-0.2.0.dist-info/entry_points.txt
czapi-0.2.0.dist-info/top_level.txt
czapi-0.2.0.dist-info/RECORD
