Metadata-Version: 2.1
Name: czapi
Version: 0.2.0
Summary: CurlingZone scraper API.
Home-page: https://github.com/calicorob/czapi/tree/master/
Author: Robert Currie
Author-email: robert.art.currie@gmail.com
License: Apache Software License 2.0
Keywords: curling,stats
Platform: UNKNOWN
Classifier: Development Status :: 3 - Alpha
Classifier: Intended Audience :: Developers
Classifier: Natural Language :: English
Classifier: Programming Language :: Python :: 3.6
Classifier: Programming Language :: Python :: 3.7
Classifier: Programming Language :: Python :: 3.8
Classifier: License :: OSI Approved :: Apache Software License
Requires-Python: >=3.6
License-File: LICENSE
Requires-Dist: pip
Requires-Dist: packaging
Requires-Dist: bs4
Requires-Dist: requests
Provides-Extra: dev
